[{"collectionId":"xd6ghjd8qgmpj78","collectionName":"tools_properties","collectionid":"uzicjlqmxnvysme","created":"2023-05-31 17:56:33.981Z","id":"isztzpunaqxdfcf","propactive":"true","propappend":"","propcolor":"","propcolumntype":"Normal","propdatatype":"String","propdateformat":"Y-m-d H:i","propdesc":"","propdisplayformat":"F j, Y","propenabled":"true","propforeigndisplayfield":"","propforeignfield":"","propforeigntable":"","propheight":"","propicon":"","proplocale":"en","propmax":"100","propmaxlen":"","propname":"id","propoptions":"","proppos":"00","propprefix":"","propprepend":"","propreadonly":"false","proprequired":"false","proprows":"","propshape":"","propsize":"","propstart":"0","propstep":"1","propsuffix":"","proptime24":"false","proptitle":"#","proptooltippos":"left","proptype":"TextBox","propupdate":"","propurl":"","propvalue":"","propvisible":"false","propwidth":"","updated":"2023-06-10 00:48:22.933Z","expand":{}},{"collectionId":"xd6ghjd8qgmpj78","collectionName":"tools_properties","collectionid":"uzicjlqmxnvysme","created":"2023-05-31 17:55:39.428Z","id":"ygrwonwdowsfsko","propactive":"true","propappend":"","propcolor":"","propcolumntype":"Normal","propdatatype":"String","propdateformat":"Y-m-d H:i","propdesc":"","propdisplayformat":"F j, Y","propenabled":"true","propforeigndisplayfield":"name","propforeignfield":"id","propforeigntable":"ociiynqsnxxjekw","propheight":"","propicon":"","proplocale":"en","propmax":"100","propmaxlen":"","propname":"customer","propoptions":"","proppos":"02","propprefix":"","propprepend":"","propreadonly":"false","proprequired":"true","proprows":"","propshape":"","propsize":"","propstart":"0","propstep":"1","propsuffix":"","proptime24":"false","proptitle":"Customer","proptooltippos":"left","proptype":"Select","propupdate":"","propurl":"","propvalue":"","propvisible":"true","propwidth":"","updated":"2023-06-05 14:14:04.714Z","expand":{}},{"collectionId":"xd6ghjd8qgmpj78","collectionName":"tools_properties","collectionid":"uzicjlqmxnvysme","created":"2023-06-10 00:46:55.008Z","id":"uzgoodutdhwkcno","propactive":"true","propappend":"fa-solid fa-magnifying-glass","propcolor":"","propcolumntype":"Select","propdatatype":"String","propdateformat":"Y-m-d H:i","propdesc":"","propdisplayformat":"F j, Y","propenabled":"true","propforeigndisplayfield":"name","propforeignfield":"id","propforeigntable":"sennzyprlcneder","propheight":"","propicon":"","proplocale":"","propmax":"100","propmaxlen":"","propname":"emailtemplate","propoptions":"","proppos":"02","propprefix":"","propprepend":"","propreadonly":"false","proprequired":"true","proprows":"","propshape":"","propsize":"","propstart":"0","propstep":"1","propsuffix":"","proptime24":"false","proptitle":"Template","proptooltippos":"left","proptype":"SelectGroup","propupdate":"","propurl":"","propvalue":"","propvisible":"true","propwidth":"","updated":"2023-06-10 00:50:57.878Z","expand":{}},{"collectionId":"xd6ghjd8qgmpj78","collectionName":"tools_properties","collectionid":"uzicjlqmxnvysme","created":"2023-05-31 17:56:49.907Z","id":"vewrtflxdaeudok","propactive":"true","propappend":"","propcolor":"","propcolumntype":"Email","propdatatype":"String","propdateformat":"Y-m-d H:i","propdesc":"","propdisplayformat":"F j, Y","propenabled":"true","propforeigndisplayfield":"","propforeignfield":"","propforeigntable":"","propheight":"","propicon":"","proplocale":"en","propmax":"100","propmaxlen":"","propname":"email","propoptions":"","proppos":"03","propprefix":"","propprepend":"","propreadonly":"false","proprequired":"true","proprows":"","propshape":"","propsize":"","propstart":"0","propstep":"1","propsuffix":"","proptime24":"false","proptitle":"Email","proptooltippos":"left","proptype":"TextBox","propupdate":"","propurl":"","propvalue":"","propvisible":"true","propwidth":"","updated":"2023-06-05 14:14:05.457Z","expand":{}},{"collectionId":"xd6ghjd8qgmpj78","collectionName":"tools_properties","collectionid":"uzicjlqmxnvysme","created":"2023-05-31 18:39:19.691Z","id":"mmmdfmgohatldup","propactive":"true","propappend":"","propcolor":"","propcolumntype":"Normal","propdatatype":"String","propdateformat":"Y-m-d H:i","propdesc":"","propdisplayformat":"F j, Y","propenabled":"true","propforeigndisplayfield":"","propforeignfield":"","propforeigntable":"","propheight":"","propicon":"","proplocale":"en","propmax":"100","propmaxlen":"","propname":"subject","propoptions":"","proppos":"04","propprefix":"","propprepend":"","propreadonly":"false","proprequired":"true","proprows":"","propshape":"","propsize":"","propstart":"0","propstep":"1","propsuffix":"","proptime24":"false","proptitle":"Subject","proptooltippos":"left","proptype":"TextBox","propupdate":"","propurl":"","propvalue":"","propvisible":"true","propwidth":"","updated":"2023-06-05 14:14:06.227Z","expand":{}},{"collectionId":"xd6ghjd8qgmpj78","collectionName":"tools_properties","collectionid":"uzicjlqmxnvysme","created":"2023-05-31 17:57:49.021Z","id":"yvrsvlazhffsjua","propactive":"true","propappend":"","propcolor":"","propcolumntype":"Normal","propdatatype":"String","propdateformat":"Y-m-d H:i","propdesc":"","propdisplayformat":"F j, Y","propenabled":"true","propforeigndisplayfield":"","propforeignfield":"","propforeigntable":"","propheight":"","propicon":"","proplocale":"en","propmax":"100","propmaxlen":"","propname":"message","propoptions":"","proppos":"05","propprefix":"","propprepend":"","propreadonly":"false","proprequired":"true","proprows":"10","propshape":"","propsize":"","propstart":"0","propstep":"1","propsuffix":"","proptime24":"false","proptitle":"Message","proptooltippos":"left","proptype":"TextArea","propupdate":"","propurl":"","propvalue":"","propvisible":"true","propwidth":"","updated":"2023-06-05 14:14:07.582Z","expand":{}},{"collectionId":"xd6ghjd8qgmpj78","collectionName":"tools_properties","collectionid":"uzicjlqmxnvysme","created":"2023-05-31 19:03:44.569Z","id":"nmnzbhjtagusjad","propactive":"true","propappend":"","propcolor":"success","propcolumntype":"Toggle","propdatatype":"String","propdateformat":"Y-m-d H:i","propdesc":"","propdisplayformat":"F j, Y","propenabled":"true","propforeigndisplayfield":"","propforeignfield":"","propforeigntable":"","propheight":"","propicon":"","proplocale":"en","propmax":"100","propmaxlen":"","propname":"schedule","propoptions":"","proppos":"06","propprefix":"","propprepend":"","propreadonly":"false","proprequired":"false","proprows":"","propshape":"","propsize":"","propstart":"0","propstep":"1","propsuffix":"","proptime24":"false","proptitle":"Schedule","proptooltippos":"left","proptype":"Toggle","propupdate":"","propurl":"","propvalue":"","propvisible":"true","propwidth":"","updated":"2023-06-05 14:14:08.411Z","expand":{}},{"collectionId":"xd6ghjd8qgmpj78","collectionName":"tools_properties","collectionid":"uzicjlqmxnvysme","created":"2023-05-31 19:05:57.803Z","id":"ljojtoamqkhiaac","propactive":"true","propappend":"","propcolor":"success","propcolumntype":"Toggle","propdatatype":"String","propdateformat":"Y-m-d H:i","propdesc":"","propdisplayformat":"F j, Y","propenabled":"true","propforeigndisplayfield":"","propforeignfield":"","propforeigntable":"","propheight":"","propicon":"","proplocale":"en","propmax":"100","propmaxlen":"","propname":"sent","propoptions":"","proppos":"07","propprefix":"","propprepend":"","propreadonly":"true","proprequired":"false","proprows":"","propshape":"","propsize":"","propstart":"0","propstep":"1","propsuffix":"","proptime24":"false","proptitle":"Sent","proptooltippos":"left","proptype":"Toggle","propupdate":"","propurl":"","propvalue":"","propvisible":"true","propwidth":"","updated":"2023-06-05 14:14:09.558Z","expand":{}},{"collectionId":"xd6ghjd8qgmpj78","collectionName":"tools_properties","collectionid":"uzicjlqmxnvysme","created":"2023-05-31 19:04:20.423Z","id":"bjvosolcoebutlm","propactive":"true","propappend":"","propcolor":"","propcolumntype":"DateTime","propdatatype":"String","propdateformat":"Y-m-d H:i","propdesc":"","propdisplayformat":"F j, Y","propenabled":"true","propforeigndisplayfield":"","propforeignfield":"","propforeigntable":"","propheight":"","propicon":"","proplocale":"en","propmax":"100","propmaxlen":"","propname":"datesent","propoptions":"","proppos":"08","propprefix":"","propprepend":"","propreadonly":"false","proprequired":"false","proprows":"","propshape":"","propsize":"","propstart":"0","propstep":"1","propsuffix":"","proptime24":"false","proptitle":"Date Sent","proptooltippos":"left","proptype":"Label","propupdate":"","propurl":"","propvalue":"","propvisible":"true","propwidth":"","updated":"2023-06-05 14:14:11.341Z","expand":{}}]