[{"collectionId":"xd6ghjd8qgmpj78","collectionName":"tools_properties","collectionid":"wcajhzsyhqhkwjf","created":"2023-05-28 13:17:48.833Z","id":"ruvvdbcxscmzzjv","propactive":"true","propappend":"","propcolor":"","propcolumntype":"Normal","propdatatype":"String","propdateformat":"Y-m-d H:i","propdesc":"","propdisplayformat":"F j, Y","propenabled":"true","propforeigndisplayfield":"","propforeignfield":"","propforeigntable":"","propheight":"","propicon":"","proplocale":"en","propmax":"100","propmaxlen":"","propname":"x_tranid","propoptions":"","proppos":"02","propprefix":"","propprepend":"","propreadonly":"false","proprequired":"false","proprows":"","propshape":"","propsize":"","propstart":"0","propstep":"1","propsuffix":"","proptime24":"false","proptitle":"ID","proptooltippos":"left","proptype":"TextBox","propupdate":"","propurl":"","propvalue":"","propvisible":"true","propwidth":"","updated":"2023-06-04 12:56:59.167Z","expand":{}},{"collectionId":"xd6ghjd8qgmpj78","collectionName":"tools_properties","collectionid":"wcajhzsyhqhkwjf","created":"2023-05-28 13:18:22.334Z","id":"iuqgebgcfqqxdps","propactive":"true","propappend":"","propcolor":"","propcolumntype":"DatePicker","propdatatype":"String","propdateformat":"Y-m-d H:i","propdesc":"","propdisplayformat":"F j, Y","propenabled":"true","propforeigndisplayfield":"","propforeignfield":"","propforeigntable":"","propheight":"","propicon":"","proplocale":"en","propmax":"100","propmaxlen":"","propname":"x_trandate","propoptions":"","proppos":"03","propprefix":"","propprepend":"","propreadonly":"false","proprequired":"false","proprows":"","propshape":"","propsize":"","propstart":"0","propstep":"1","propsuffix":"","proptime24":"false","proptitle":"Date","proptooltippos":"left","proptype":"DatePicker","propupdate":"","propurl":"","propvalue":"","propvisible":"true","propwidth":"","updated":"2023-06-04 12:57:06.904Z","expand":{}},{"collectionId":"xd6ghjd8qgmpj78","collectionName":"tools_properties","collectionid":"wcajhzsyhqhkwjf","created":"2023-05-28 13:19:42.579Z","id":"bsqdtoddxsbtegp","propactive":"true","propappend":"","propcolor":"","propcolumntype":"Normal","propdatatype":"String","propdateformat":"Y-m-d H:i","propdesc":"","propdisplayformat":"F j, Y","propenabled":"true","propforeigndisplayfield":"","propforeignfield":"","propforeigntable":"","propheight":"","propicon":"","proplocale":"en","propmax":"100","propmaxlen":"","propname":"x_name","propoptions":"","proppos":"04","propprefix":"","propprepend":"","propreadonly":"false","proprequired":"false","proprows":"","propshape":"","propsize":"","propstart":"0","propstep":"1","propsuffix":"","proptime24":"false","proptitle":"Name","proptooltippos":"left","proptype":"TextBox","propupdate":"","propurl":"","propvalue":"","propvisible":"true","propwidth":"","updated":"2023-06-04 12:57:12.022Z","expand":{}},{"collectionId":"xd6ghjd8qgmpj78","collectionName":"tools_properties","collectionid":"wcajhzsyhqhkwjf","created":"2023-05-28 13:20:06.254Z","id":"kapxhiyqhwfdgyu","propactive":"true","propappend":"","propcolor":"","propcolumntype":"Normal","propdatatype":"String","propdateformat":"Y-m-d H:i","propdesc":"","propdisplayformat":"F j, Y","propenabled":"true","propforeigndisplayfield":"","propforeignfield":"","propforeigntable":"","propheight":"","propicon":"","proplocale":"en","propmax":"100","propmaxlen":"","propname":"x_trantype","propoptions":"","proppos":"05","propprefix":"","propprepend":"","propreadonly":"false","proprequired":"false","proprows":"","propshape":"","propsize":"","propstart":"0","propstep":"1","propsuffix":"","proptime24":"false","proptitle":"Type","proptooltippos":"left","proptype":"TextBox","propupdate":"","propurl":"","propvalue":"","propvisible":"true","propwidth":"","updated":"2023-06-04 12:57:16.519Z","expand":{}},{"collectionId":"xd6ghjd8qgmpj78","collectionName":"tools_properties","collectionid":"wcajhzsyhqhkwjf","created":"2023-05-28 13:20:26.961Z","id":"ulavvgvuhlqsyqi","propactive":"true","propappend":"","propcolor":"","propcolumntype":"Normal","propdatatype":"String","propdateformat":"Y-m-d H:i","propdesc":"","propdisplayformat":"F j, Y","propenabled":"true","propforeigndisplayfield":"","propforeignfield":"","propforeigntable":"","propheight":"","propicon":"","proplocale":"en","propmax":"100","propmaxlen":"","propname":"x_status","propoptions":"","proppos":"06","propprefix":"","propprepend":"","propreadonly":"false","proprequired":"false","proprows":"","propshape":"","propsize":"","propstart":"0","propstep":"1","propsuffix":"","proptime24":"false","proptitle":"Status","proptooltippos":"left","proptype":"TextBox","propupdate":"","propurl":"","propvalue":"","propvisible":"true","propwidth":"","updated":"2023-06-04 12:57:30.977Z","expand":{}},{"collectionId":"xd6ghjd8qgmpj78","collectionName":"tools_properties","collectionid":"wcajhzsyhqhkwjf","created":"2023-05-28 13:23:43.461Z","id":"zsnijadecjzulec","propactive":"true","propappend":"","propcolor":"success","propcolumntype":"Email","propdatatype":"String","propdateformat":"Y-m-d H:i","propdesc":"","propdisplayformat":"F j, Y","propenabled":"true","propforeigndisplayfield":"","propforeignfield":"","propforeigntable":"","propheight":"","propicon":"","proplocale":"en","propmax":"100","propmaxlen":"","propname":"x_tranfrom","propoptions":"","proppos":"11","propprefix":"","propprepend":"","propreadonly":"false","proprequired":"false","proprows":"","propshape":"","propsize":"","propstart":"0","propstep":"1","propsuffix":"","proptime24":"false","proptitle":"From","proptooltippos":"left","proptype":"TextBox","propupdate":"","propurl":"","propvalue":"","propvisible":"true","propwidth":"","updated":"2023-06-04 12:57:35.632Z","expand":{}},{"collectionId":"xd6ghjd8qgmpj78","collectionName":"tools_properties","collectionid":"wcajhzsyhqhkwjf","created":"2023-05-28 13:24:01.068Z","id":"dtuclcacfaoxmwr","propactive":"true","propappend":"","propcolor":"success","propcolumntype":"Email","propdatatype":"String","propdateformat":"Y-m-d H:i","propdesc":"","propdisplayformat":"F j, Y","propenabled":"true","propforeigndisplayfield":"","propforeignfield":"","propforeigntable":"","propheight":"","propicon":"","proplocale":"en","propmax":"100","propmaxlen":"","propname":"x_tranto","propoptions":"","proppos":"12","propprefix":"","propprepend":"","propreadonly":"false","proprequired":"false","proprows":"","propshape":"","propsize":"","propstart":"0","propstep":"1","propsuffix":"","proptime24":"false","proptitle":"To","proptooltippos":"left","proptype":"TextBox","propupdate":"","propurl":"","propvalue":"","propvisible":"true","propwidth":"","updated":"2023-06-04 12:57:39.084Z","expand":{}},{"collectionId":"xd6ghjd8qgmpj78","collectionName":"tools_properties","collectionid":"wcajhzsyhqhkwjf","created":"2023-05-28 13:25:12.203Z","id":"jiykjukkcegrzip","propactive":"true","propappend":"","propcolor":"","propcolumntype":"Normal","propdatatype":"String","propdateformat":"Y-m-d H:i","propdesc":"","propdisplayformat":"F j, Y","propenabled":"true","propforeigndisplayfield":"","propforeignfield":"","propforeigntable":"","propheight":"","propicon":"","proplocale":"en","propmax":"100","propmaxlen":"","propname":"x_tranitem","propoptions":"","proppos":"13","propprefix":"","propprepend":"","propreadonly":"false","proprequired":"false","proprows":"","propshape":"","propsize":"","propstart":"0","propstep":"1","propsuffix":"","proptime24":"false","proptitle":"Item","proptooltippos":"left","proptype":"TextBox","propupdate":"","propurl":"","propvalue":"","propvisible":"true","propwidth":"","updated":"2023-06-04 12:57:42.739Z","expand":{}},{"collectionId":"xd6ghjd8qgmpj78","collectionName":"tools_properties","collectionid":"wcajhzsyhqhkwjf","created":"2023-05-28 13:25:42.356Z","id":"qgcqawagkbauopf","propactive":"true","propappend":"","propcolor":"","propcolumntype":"Normal","propdatatype":"String","propdateformat":"Y-m-d H:i","propdesc":"","propdisplayformat":"F j, Y","propenabled":"true","propforeigndisplayfield":"","propforeignfield":"","propforeigntable":"","propheight":"","propicon":"","proplocale":"en","propmax":"100","propmaxlen":"","propname":"x_tranref","propoptions":"","proppos":"14","propprefix":"","propprepend":"","propreadonly":"false","proprequired":"false","proprows":"","propshape":"","propsize":"","propstart":"0","propstep":"1","propsuffix":"","proptime24":"false","proptitle":"Ref","proptooltippos":"left","proptype":"TextBox","propupdate":"","propurl":"","propvalue":"","propvisible":"true","propwidth":"","updated":"2023-06-04 12:57:46.996Z","expand":{}},{"collectionId":"xd6ghjd8qgmpj78","collectionName":"tools_properties","collectionid":"wcajhzsyhqhkwjf","created":"2023-05-28 13:28:47.021Z","id":"nallcxtyabmknhd","propactive":"true","propappend":"","propcolor":"","propcolumntype":"Normal","propdatatype":"String","propdateformat":"Y-m-d H:i","propdesc":"","propdisplayformat":"F j, Y","propenabled":"true","propforeigndisplayfield":"","propforeignfield":"","propforeigntable":"","propheight":"","propicon":"","proplocale":"en","propmax":"100","propmaxlen":"","propname":"x_subject","propoptions":"","proppos":"18","propprefix":"","propprepend":"","propreadonly":"false","proprequired":"false","proprows":"","propshape":"","propsize":"","propstart":"0","propstep":"1","propsuffix":"","proptime24":"false","proptitle":"Subject","proptooltippos":"left","proptype":"TextBox","propupdate":"","propurl":"","propvalue":"","propvisible":"true","propwidth":"","updated":"2023-06-04 12:57:50.690Z","expand":{}},{"collectionId":"xd6ghjd8qgmpj78","collectionName":"tools_properties","collectionid":"wcajhzsyhqhkwjf","created":"2023-05-28 13:29:28.132Z","id":"aldevezoailymjh","propactive":"true","propappend":"","propcolor":"","propcolumntype":"Normal","propdatatype":"String","propdateformat":"Y-m-d H:i","propdesc":"","propdisplayformat":"F j, Y","propenabled":"true","propforeigndisplayfield":"","propforeignfield":"","propforeigntable":"","propheight":"","propicon":"","proplocale":"en","propmax":"100","propmaxlen":"","propname":"x_note","propoptions":"","proppos":"19","propprefix":"","propprepend":"","propreadonly":"false","proprequired":"false","proprows":"","propshape":"","propsize":"","propstart":"0","propstep":"1","propsuffix":"","proptime24":"false","proptitle":"Note","proptooltippos":"left","proptype":"TextBox","propupdate":"","propurl":"","propvalue":"","propvisible":"true","propwidth":"","updated":"2023-06-04 12:57:55.898Z","expand":{}},{"collectionId":"xd6ghjd8qgmpj78","collectionName":"tools_properties","collectionid":"wcajhzsyhqhkwjf","created":"2023-05-28 13:31:41.744Z","id":"vznbdwebhtjdpry","propactive":"true","propappend":"","propcolor":"","propcolumntype":"Normal","propdatatype":"String","propdateformat":"Y-m-d H:i","propdesc":"","propdisplayformat":"F j, Y","propenabled":"true","propforeigndisplayfield":"","propforeignfield":"","propforeigntable":"","propheight":"","propicon":"","proplocale":"en","propmax":"100","propmaxlen":"","propname":"x_balanceimpact","propoptions":"","proppos":"20","propprefix":"","propprepend":"","propreadonly":"false","proprequired":"false","proprows":"","propshape":"","propsize":"","propstart":"0","propstep":"1","propsuffix":"","proptime24":"false","proptitle":"Impact","proptooltippos":"left","proptype":"TextBox","propupdate":"","propurl":"","propvalue":"","propvisible":"true","propwidth":"","updated":"2023-06-04 12:58:00.197Z","expand":{}}]